<annotation>
	<folder></folder>
	<filename>3wh0cgwdsis81_cropped_cropped_jpg.rf.2de4486472f8d49afc3ca94a98b56a66.jpg</filename>
	<path>3wh0cgwdsis81_cropped_cropped_jpg.rf.2de4486472f8d49afc3ca94a98b56a66.jpg</path>
	<source>
		<database>roboflow.com</database>
	</source>
	<size>
		<width>640</width>
		<height>640</height>
		<depth>3</depth>
	</size>
	<segmented>0</segmented>
	<object>
		<name>spaghetti</name>
		<pose>Unspecified</pose>
		<truncated>0</truncated>
		<difficult>0</difficult>
		<occluded>0</occluded>
		<bndbox>
			<xmin>226</xmin>
			<xmax>374</xmax>
			<ymin>147</ymin>
			<ymax>273</ymax>
		</bndbox>
	</object>
	<object>
		<name>spaghetti</name>
		<pose>Unspecified</pose>
		<truncated>0</truncated>
		<difficult>0</difficult>
		<occluded>0</occluded>
		<bndbox>
			<xmin>372</xmin>
			<xmax>461</xmax>
			<ymin>151</ymin>
			<ymax>275</ymax>
		</bndbox>
	</object>
	<object>
		<name>spaghetti</name>
		<pose>Unspecified</pose>
		<truncated>0</truncated>
		<difficult>0</difficult>
		<occluded>0</occluded>
		<bndbox>
			<xmin>297</xmin>
			<xmax>443</xmax>
			<ymin>264</ymin>
			<ymax>360</ymax>
		</bndbox>
	</object>
</annotation>
