<annotation>
	<folder></folder>
	<filename>imag-131-_jpg.rf.ec895cfcbc21a9a1e56a9e6e83e8863f.jpg</filename>
	<path>imag-131-_jpg.rf.ec895cfcbc21a9a1e56a9e6e83e8863f.jpg</path>
	<source>
		<database>roboflow.com</database>
	</source>
	<size>
		<width>640</width>
		<height>640</height>
		<depth>3</depth>
	</size>
	<segmented>0</segmented>
	<object>
		<name>spaghetti</name>
		<pose>Unspecified</pose>
		<truncated>0</truncated>
		<difficult>0</difficult>
		<occluded>0</occluded>
		<bndbox>
			<xmin>202</xmin>
			<xmax>405</xmax>
			<ymin>1</ymin>
			<ymax>459</ymax>
		</bndbox>
	</object>
</annotation>
